mementomap/__init__.py
mementomap/__main__.py
mementomap/cli.py
mementomap-0.1.0b2.dist-info/LICENSE
mementomap-0.1.0b2.dist-info/METADATA
mementomap-0.1.0b2.dist-info/WHEEL
mementomap-0.1.0b2.dist-info/entry_points.txt
mementomap-0.1.0b2.dist-info/top_level.txt
mementomap-0.1.0b2.dist-info/RECORD
