Metadata-Version: 2.1
Name: mementomap
Version: 0.1.0b2
Summary: A Tool to Summarize Web Archive Holdings
Home-page: https://github.com/oduwsdl/MementoMap
Author: Sawood Alam
Author-email: ibnesayeed@gmail.com
License: MIT License
Platform: UNKNOWN
Classifier: Programming Language :: Python :: 3
Classifier: License :: OSI Approved :: MIT License
Classifier: Operating System :: OS Independent
Classifier: Environment :: Console
Classifier: Topic :: Internet
Classifier: Topic :: Internet :: WWW/HTTP
Classifier: Topic :: Internet :: WWW/HTTP :: Indexing/Search
Classifier: Development Status :: 4 - Beta
Provides: mementomap
Requires-Python: >=3.6
License-File: LICENSE
